[
    {
        "title": "Demographics",
        "image":"/assets/images/demographics_data.webp",
        "description":"Track placed and unplaced students in each branch for seamless placement insights."
    },
    {
        "title": "Domain",
        "image":"/assets/images/domain_data.webp",
        "description":"Track placed and unplaced students in each branch for seamless placement insights."
    },
    {
        "title": "gender",
        "image":"/assets/images/gender_data.webp",
        "description":"Track placed and unplaced students in each branch for seamless placement insights."
    }

]